{"is_source_file": true, "format": "Java", "description": "Defines a collection of global error codes as constants for exception handling within the banking service project.", "external_files": [], "external_methods": [], "published": ["com.javatodev.finance.exception.GlobalErrorCode"], "classes": [{"name": "GlobalErrorCode", "description": "A class containing static string constants representing error codes for global exceptions."}], "methods": [], "calls": [], "search-terms": ["GlobalErrorCode", "ERROR_ENTITY_NOT_FOUND", "INSUFFICIENT_FUNDS", "error codes", "exceptions"], "state": 2, "file_id": 50, "knowledge_revision": 427, "git_revision": "d40361d68e14752ecdb9b13cabe0eac461f82a70", "hash": "891df5a6c9c2c493bc6cee33fbb30c82", "format-version": 4, "code-base-name": "internet-banking-concept-microservices", "filename": "core-banking-service/src/main/java/com/javatodev/finance/exception/GlobalErrorCode.java", "revision_history": [{"427": "d40361d68e14752ecdb9b13cabe0eac461f82a70"}]}